{
  code: "function",
  variantGroups: [
    { code: "side", loadFromProperties: "abstract/horizontalorientation" }
  ],
  behaviors: [
    { name: "HorizontalOrientable" },
    { name: "BlockEntityForward" }
  ],
  entityclass: "CacheMesh",
  entityBehaviors: [{name: "PortHole"}],
  creativeinventory: { general: ["*-north"] },
  blockmaterial: "Stone",
  drawtype: "json",
  shapeByType: {
    "*-north": {
      base: "block/function"
    },
    "*-east": {
      base: "block/function",
      rotateY: 270
    },
    "*-south": {
      base: "block/function",
      rotateY: 180
    },
    "*-west": {
      base: "block/function",
      rotateY: 90
    }
  },
  textures: {
    "eastwest": {
      base: "scope/eastwest",
      blendedOverlays: [{ base: "scope/function", blendMode: "ColorBurn" }]
    },
    "northsouth": {
      base: "scope/northsouth",
      blendedOverlays: [{ base: "scope/function", blendMode: "ColorBurn" }]
    },
    "up": {
      base: "scope/up",
      blendedOverlays: [{ base: "scope/function", blendMode: "ColorBurn" }]
    },
  },
  sideopaque: {
    all: true,
    up: false
  },
  sideOpaqueByType: {
    "*-north": {
      north: false,
    },
    "*-east": {
      east: false,
    },
    "*-south": {
      south: false,
    },
    "*-west": {
      west: false,
    }
  },
  sidesolid: {
    all: true
  },
  resistance: 3.5,
  sounds: {
    place: "game:block/ceramicplace",
    walk: "game:walk/stone1"
  }
}